google_api/__init__.py
google_api/config.py
google_api/gmail.py
google_api_rdw-0.0.2.dist-info/LICENSE
google_api_rdw-0.0.2.dist-info/METADATA
google_api_rdw-0.0.2.dist-info/WHEEL
google_api_rdw-0.0.2.dist-info/top_level.txt
google_api_rdw-0.0.2.dist-info/RECORD
