Metadata-Version: 2.1
Name: google-api-rdw
Version: 0.0.2
Summary: Connect to the google api
Home-page: https://github.com/robertdavidwest/google_api
Author: Robert West
Author-email: robert.david.west@gmail.com
License: MIT
Platform: UNKNOWN
